dbapihelper/__init__.py
dbapihelper/__version__.py
dbapihelper/connection.py
dbapihelper/console.py
dbapihelper/cursor.py
dbapihelper/exceptions.py
dbapihelper/utils.py
dbapihelper-0.1.2.dist-info/LICENSE
dbapihelper-0.1.2.dist-info/METADATA
dbapihelper-0.1.2.dist-info/WHEEL
dbapihelper-0.1.2.dist-info/top_level.txt
dbapihelper-0.1.2.dist-info/RECORD
