Metadata-Version: 2.1
Name: dbapihelper
Version: 0.1.2
Summary: A helper library for writing Python DB API 2.0 modules
Home-page: https://github.com/betodealmeida/dbapihelper
Author: Beto Dealmeida
Author-email: beto@dealmeida.net
License: MIT
Platform: UNKNOWN
Classifier: License :: OSI Approved :: MIT License
Classifier: Programming Language :: Python
Classifier: Programming Language :: Python :: 3.6
Classifier: Programming Language :: Python :: 3.7
Classifier: Programming Language :: Python :: Implementation :: CPython
Classifier: Programming Language :: Python :: Implementation :: PyPy
Requires-Dist: six
Provides-Extra: cli
Requires-Dist: pygments ; extra == 'cli'
Requires-Dist: prompt-toolkit (>=2) ; extra == 'cli'
Requires-Dist: tabulate ; extra == 'cli'
Provides-Extra: dev
Requires-Dist: coverage ; extra == 'dev'
Requires-Dist: flake8 ; extra == 'dev'
Requires-Dist: nose ; extra == 'dev'
Requires-Dist: pipreqs ; extra == 'dev'
Requires-Dist: pytest (>=2.8) ; extra == 'dev'
Requires-Dist: pytest-cov ; extra == 'dev'
Requires-Dist: requests-mock ; extra == 'dev'
Requires-Dist: twine ; extra == 'dev'
